yeedu/__init__.py
yeedu/hooks/__init__.py
yeedu/hooks/yeedu.py
yeedu/operators/__init__.py
yeedu/operators/yeedu.py
yeedu_job_run_operator_test-2.0.0.dist-info/LICENSE
yeedu_job_run_operator_test-2.0.0.dist-info/METADATA
yeedu_job_run_operator_test-2.0.0.dist-info/WHEEL
yeedu_job_run_operator_test-2.0.0.dist-info/top_level.txt
yeedu_job_run_operator_test-2.0.0.dist-info/RECORD
