Metadata-Version: 2.1
Name: yeedu-job-run-operator-test
Version: 2.0.0
Project-URL: GitHub, https://github.com/rohith-sagar/AirflowYeeduOperator.git
License-File: LICENSE
Requires-Dist: apache-airflow (>=2.7.3)
